kibot/__init__.py
kibot/__main__.py
kibot/banner.py
kibot/config_reader.py
kibot/create_pdf.py
kibot/dep_downloader.py
kibot/docopt.py
kibot/drill_marks.py
kibot/error.py
kibot/fil_base.py
kibot/fil_expand_text_vars.py
kibot/fil_field_modify.py
kibot/fil_field_rename.py
kibot/fil_generic.py
kibot/fil_rot_footprint.py
kibot/fil_separate_pins.py
kibot/fil_spec_to_field.py
kibot/fil_subparts.py
kibot/fil_urlify.py
kibot/fil_value_split.py
kibot/fil_var_rename.py
kibot/fil_var_rename_kicost.py
kibot/globals.py
kibot/gs.py
kibot/kiplot.py
kibot/layer.py
kibot/log.py
kibot/macros.py
kibot/misc.py
kibot/optionable.py
kibot/out_any_diff.py
kibot/out_any_drill.py
kibot/out_any_layer.py
kibot/out_any_navigate_results.py
kibot/out_any_pcb_print.py
kibot/out_any_sch_print.py
kibot/out_any_stencil.py
kibot/out_base.py
kibot/out_base_3d.py
kibot/out_blender_export.py
kibot/out_boardview.py
kibot/out_bom.py
kibot/out_compress.py
kibot/out_copy_files.py
kibot/out_diff.py
kibot/out_download_datasheets.py
kibot/out_dxf.py
kibot/out_dxf_sch_print.py
kibot/out_excellon.py
kibot/out_export_3d.py
kibot/out_gencad.py
kibot/out_gerb_drill.py
kibot/out_gerber.py
kibot/out_hpgl.py
kibot/out_hpgl_sch_print.py
kibot/out_ibom.py
kibot/out_info.py
kibot/out_ipc2581.py
kibot/out_jobset.py
kibot/out_kibom.py
kibot/out_kicanvas.py
kibot/out_kicost.py
kibot/out_kikit_present.py
kibot/out_kiri.py
kibot/out_navigate_results.py
kibot/out_navigate_results_rb.py
kibot/out_netlist.py
kibot/out_odb.py
kibot/out_panelize.py
kibot/out_pcb2blender_tools.py
kibot/out_pcb_print.py
kibot/out_pcb_variant.py
kibot/out_pcbdraw.py
kibot/out_pdf.py
kibot/out_pdf_pcb_print.py
kibot/out_pdf_sch_print.py
kibot/out_pdfunite.py
kibot/out_populate.py
kibot/out_position.py
kibot/out_ps.py
kibot/out_ps_sch_print.py
kibot/out_qr_lib.py
kibot/out_render_3d.py
kibot/out_report.py
kibot/out_sch_variant.py
kibot/out_stencil_3d.py
kibot/out_stencil_for_jig.py
kibot/out_step.py
kibot/out_svg.py
kibot/out_svg_pcb_print.py
kibot-1.8.4.dist-info/LICENSE
kibot-1.8.4.dist-info/METADATA
kibot-1.8.4.dist-info/WHEEL
kibot-1.8.4.dist-info/entry_points.txt
kibot-1.8.4.dist-info/top_level.txt
kibot-1.8.4.dist-info/RECORD
