Metadata-Version: 2.1
Name: kibot
Version: 1.8.4
Summary: KiCad automation tool for documents generation
Home-page: https://github.com/INTI-CMNB/KiBot/
Author: Salvador E. Tropea, John Beard
Author-email: stropea@inti.gob.ar
License: GPL-3.0
Platform: POSIX
Classifier: Development Status :: 5 - Production/Stable
Classifier: Environment :: Console
Classifier: Intended Audience :: Developers
Classifier: License :: OSI Approved :: GNU General Public License v3 or later (GPLv3+)
Classifier: Natural Language :: English
Classifier: Operating System :: OS Independent
Classifier: Programming Language :: Python :: 3
Classifier: Topic :: Scientific/Engineering :: Electronic Design Automation (EDA)
Requires-Python: >=3.7
Requires-Dist: colorama
Requires-Dist: kiauto
Requires-Dist: lark
Requires-Dist: markdown2
Requires-Dist: pyyaml
Requires-Dist: qrcodegen
Requires-Dist: requests
Requires-Dist: xlsxwriter
